{
"companyName": "Alliance Bank Malaysia Berhad",
"productName": "AEIOU 5 Quiz Trivia",
"productVersion": "1.0",
"dataUrl": "WebGL Build 02092019.data.unityweb",
"wasmCodeUrl": "WebGL Build 02092019.wasm.code.unityweb",
"wasmFrameworkUrl": "WebGL Build 02092019.wasm.framework.unityweb",
"graphicsAPI": ["WebGL 2.0","WebGL 1.0"],
"webglContextAttributes": {"preserveDrawingBuffer": false},
"splashScreenStyle": "Light",
"backgroundColor": "#989797",
"cacheControl": {"default": "must-revalidate"},
"developmentBuild": false,
"multithreading": false,
"unityVersion": "2019.3.0b1"
}